.coveragerc
.gitignore
.travis.yml
LICENSE
README
README.md
runtests.py
setup.cfg
setup.py
doc/Makefile
doc/conf.py
doc/index.rst
doc/installation.rst
doc/modules.rst
doc/opm_reference.rst
doc/opm_usage.rst
doc/user.rst
odmpy/__init__.py
odmpy/opm.py
odmpy.egg-info/PKG-INFO
odmpy.egg-info/SOURCES.txt
odmpy.egg-info/dependency_links.txt
odmpy.egg-info/requires.txt
odmpy.egg-info/top_level.txt
odmpy/tests/test_helpers.py
odmpy/tests/test_opm.py
odmpy/tests/valid.opm.txt
shovel/doc.py
shovel/readme.py