Metadata-Version: 1.1
Name: odmpy
Version: 0.2.4
Summary: Create valid ASCII OPM, OMM, and OEM files.
Home-page: https://github.com/RazerM/odmpy
Author: Frazer McLean
Author-email: frazer@frazermclean.co.uk
License: MIT
Platform: UNKNOWN
Classifier: Development Status :: 3 - Alpha
Classifier: Intended Audience :: Science/Research
Classifier: Topic :: Scientific/Engineering :: Astronomy
Classifier: License :: OSI Approved :: MIT License
Classifier: Programming Language :: Python :: 3
Classifier: Programming Language :: Python :: 3.0
Classifier: Programming Language :: Python :: 3.1
Classifier: Programming Language :: Python :: 3.2
Classifier: Programming Language :: Python :: 3.3
Classifier: Programming Language :: Python :: 3.4
